ultratypetest_cli/__init__.py
ultratypetest_cli/__main__.py
ultratypetest_cli/py.typed
ultratypetest_cli/texts.txt
ultratypetest_cli-0.1.1.dist-info/METADATA
ultratypetest_cli-0.1.1.dist-info/WHEEL
ultratypetest_cli-0.1.1.dist-info/entry_points.txt
ultratypetest_cli-0.1.1.dist-info/licenses/LICENSE
ultratypetest_cli-0.1.1.dist-info/RECORD
