Metadata-Version: 2.4
Name: ultratypetest-cli
Version: 0.1.1
Summary: Typing test CLI tool
Project-URL: Homepage, https://github.com/JaiSuryaPrabu/ultratypetest-cli
Project-URL: Repository, https://github.com/JaiSuryaPrabu/ultratypetest-cli
Author-email: Jaisurya <pjaisurya.ml@gmail.com>
License-File: LICENSE
Classifier: Environment :: Console :: Curses
Classifier: License :: OSI Approved :: MIT License
Classifier: Operating System :: OS Independent
Classifier: Programming Language :: Python :: 3
Classifier: Topic :: Terminals
Requires-Python: ==3.13.2
Requires-Dist: windows-curses; sys_platform == 'win32'
